polaris/__init__.py
polaris/loop.py
polaris/loopPool.py
polaris/loopScore.py
polaris/polaris.py
polaris/version.py
polaris_loop-1.0.0.dist-info/METADATA
polaris_loop-1.0.0.dist-info/WHEEL
polaris_loop-1.0.0.dist-info/entry_points.txt
polaris_loop-1.0.0.dist-info/top_level.txt
polaris_loop-1.0.0.dist-info/RECORD
