Metadata-Version: 2.1
Name: polaris_loop
Version: 1.0.0
Summary: A Unified Axial-aware Framework for Chromatin Loop Annotation in Bulk and Single-cell Hi-C Data
Home-page: https://github.com/compbiodsa/Polaris
Author: Yusen HOU, Yanlin Zhang
Author-email: yhou925@connect.hkust-gz.edu.cn
Classifier: Programming Language :: Python :: 3
Classifier: Intended Audience :: Science/Research
Classifier: Topic :: Scientific/Engineering :: Bio-Informatics
Classifier: Operating System :: OS Independent
Requires-Python: >=3.9
Requires-Dist: Click
